{
	"dealerPos": {
		"x": 320,
		"y": 431
	},
	"otherSeatPos": {
		"x": 52,
		"y": 566
	},
	"myPos": {
		"x": 588,
		"y": 1000
	},
	"seatPos": [
		{
			"x": 45,
			"y": 660
		},
		{
			"x": 45,
			"y": 800
		},
		{
			"x": 184,
			"y": 900
		},
		{
			"x": 320,
			"y": 900
		},
		{
			"x": 456,
			"y": 900
		},
		{
			"x": 595,
			"y": 800
		},
		{
			"x": 595,
			"y": 660
		}
	],
	"seatPos_jinMi": [
		{
			"x": 45,
			"y": 650
		},
		{
			"x": 45,
			"y": 850
		},
		{
			"x": 320,
			"y": 914
		},
		{
			"x": 595,
			"y": 850
		},
		{
			"x": 595,
			"y": 650
		}
	],
	"seatPos_LHD": [
		{
			"x": 45,
			"y": 910
		},
		{
			"x": 180,
			"y": 920
		},
		{
			"x": 320,
			"y": 930
		},
		{
			"x": 450,
			"y": 920
		},
		{
			"x": 595,
			"y": 910
		}
	],
	"moreSeatPos": {
		"x": 150,
		"y": 125
	},
	"betSetting": {
		"x": 237,
		"y": -50
	},
	"betPrice": [
		1,
		5,
		10,
		50,
		100,
		500,
		1000,
		2000,
		5000,
		10000,
		50000,
		100000,
		500000
	],
	"betPriceToIcon": {
		"1": 0,
		"5": 1,
		"10": 2,
		"50": 3,
		"100": 4,
		"500": 5,
		"1000": 6,
		"2000": 7,
		"5000": 8,
		"10000": 9,
		"50000": 10,
		"100000": 11,
		"500000": 12
	},
	"RGBstr": {
		"0": "0",
		"1": "1",
		"2": "2",
		"3": "3",
		"4": "4",
		"5": "5",
		"6": "6",
		"7": "7",
		"8": "8",
		"9": "9",
		"10": "A",
		"11": "B",
		"12": "C",
		"13": "D",
		"14": "E",
		"15": "F"
	},
	"maxHistoryLength": 120,
	"areaOdds": [
		0,
		2,
		2,
		8,
		11,
		11
	],
	"maskServerIds": []
}